auraxium/__init__.py
auraxium/_cache.py
auraxium/_client.py
auraxium/_log.py
auraxium/_proxy.py
auraxium/_rest.py
auraxium/_support.py
auraxium/base.py
auraxium/endpoints.py
auraxium/errors.py
auraxium/py.typed
auraxium/types.py
auraxium/census/__init__.py
auraxium/census/_query.py
auraxium/census/_support.py
auraxium/census/_urlgen.py
auraxium/event/__init__.py
auraxium/event/_client.py
auraxium/event/_trigger.py
auraxium/models/__init__.py
auraxium/models/_ability.py
auraxium/models/_achievement.py
auraxium/models/_armour.py
auraxium/models/_character.py
auraxium/models/_currency.py
auraxium/models/_depot.py
auraxium/models/_directive.py
auraxium/models/_effect.py
auraxium/models/_events.py
auraxium/models/_experience.py
auraxium/models/_faction.py
auraxium/models/_fire.py
auraxium/models/_item.py
auraxium/models/_map.py
auraxium/models/_metagame.py
auraxium/models/_objective.py
auraxium/models/_outfit.py
auraxium/models/_profile.py
auraxium/models/_projectile.py
auraxium/models/_resist.py
auraxium/models/_reward.py
auraxium/models/_skill.py
auraxium/models/_states.py
auraxium/models/_vehicle.py
auraxium/models/_weapon.py
auraxium/models/_world.py
auraxium/models/_zone.py
auraxium/models/base.py
auraxium/ps2/__init__.py
auraxium/ps2/_ability.py
auraxium/ps2/_achievement.py
auraxium/ps2/_armour.py
auraxium/ps2/_character.py
auraxium/ps2/_currency.py
auraxium/ps2/_depot.py
auraxium/ps2/_directive.py
auraxium/ps2/_effect.py
auraxium/ps2/_experience.py
auraxium/ps2/_faction.py
auraxium/ps2/_fire.py
auraxium/ps2/_item.py
auraxium/ps2/_map.py
auraxium/ps2/_metagame.py
auraxium/ps2/_objective.py
auraxium/ps2/_outfit.py
auraxium/ps2/_profile.py
auraxium/ps2/_projectile.py
auraxium/ps2/_resist.py
auraxium/ps2/_reward.py
auraxium/ps2/_skill.py
auraxium/ps2/_states.py
auraxium/ps2/_vehicle.py
auraxium/ps2/_weapon.py
auraxium/ps2/_world.py
auraxium/ps2/_zone.py
auraxium/ps2/leaderboard.py
auraxium-0.4.0.dist-info/licenses/LICENSE
auraxium-0.4.0.dist-info/METADATA
auraxium-0.4.0.dist-info/WHEEL
auraxium-0.4.0.dist-info/top_level.txt
auraxium-0.4.0.dist-info/RECORD
