Metadata-Version: 2.4
Name: auraxium
Version: 0.4.0
Summary: A python wrapper for the PlanetSide 2 Census API.
Home-page: https://github.com/leonhard-s/auraxium
Author: Leonhard S.
Author-email: leonhard-sei@outlook.com
License: MIT
Keywords: auraxium python daybreak census planetside ps2
Classifier: Development Status :: 5 - Production/Stable
Classifier: Programming Language :: Python :: 3.9
Classifier: Programming Language :: Python :: 3.10
Classifier: Programming Language :: Python :: 3.11
Classifier: Programming Language :: Python :: 3.12
Classifier: Programming Language :: Python :: 3.13
Classifier: License :: OSI Approved :: MIT License
Classifier: Operating System :: OS Independent
License-File: LICENSE
Requires-Dist: aiohttp>=3.8.0
Requires-Dist: backoff>=2.1.2
Requires-Dist: pydantic>=2.0.3
Requires-Dist: yarl>=1.7.0
Requires-Dist: websockets>=10.0
Dynamic: author
Dynamic: author-email
Dynamic: classifier
Dynamic: description
Dynamic: description-content-type
Dynamic: home-page
Dynamic: keywords
Dynamic: license
Dynamic: license-file
Dynamic: requires-dist
Dynamic: summary
